bishograd/__init__.py
bishograd/engine.py
bishograd/nn.py
bishograd-0.1.0.dist-info/METADATA
bishograd-0.1.0.dist-info/WHEEL
bishograd-0.1.0.dist-info/RECORD
