Metadata-Version: 2.3
Name: bishograd
Version: 0.1.0
Summary: Tiny & Light weight Machine Learning Library
Author-email: AK3847 <abdulkadir87633@gmail.com>
Requires-Python: >=3.8
